LICENSE
MANIFEST.in
README.rst
setup.cfg
setup.py
tests/__init__.py
tests/test_link_block.py
tests/test_settings.py
tests/test_template_tag.py
wagtail_lightadmin/__init__.py
wagtail_lightadmin/models.py
wagtail_lightadmin/rich_text.py
wagtail_lightadmin/wagtail_hooks.py
wagtail_lightadmin/widgets.py
wagtail_lightadmin.egg-info/PKG-INFO
wagtail_lightadmin.egg-info/SOURCES.txt
wagtail_lightadmin.egg-info/dependency_links.txt
wagtail_lightadmin.egg-info/not-zip-safe
wagtail_lightadmin.egg-info/requires.txt
wagtail_lightadmin.egg-info/top_level.txt
wagtail_lightadmin/static/css/admin_editor.css
wagtail_lightadmin/static/js/wagtailadmin/admin_link_widget.js
wagtail_lightadmin/static/js/wagtailadmin/lighter-hallo-bootstrap.js
wagtail_lightadmin/templates/wagtailadmin/widgets/link_chooser.html
wagtail_lightadmin/templatetags/__init__.py
wagtail_lightadmin/templatetags/pagechooser_fallback.py