Metadata-Version: 1.1
Name: wagtail-lightadmin
Version: 0.12.2
Summary: A lighter admin for wagtail
Home-page: https://github.com/leukeleu/wagtail_lightadmin
Author: Leukeleu
Author-email: info@leukeleu.nl
License: MIT
Keywords: wagtail,admin,light
Platform: UNKNOWN
Classifier: Intended Audience :: Developers
Classifier: License :: OSI Approved :: MIT License
Classifier: Operating System :: OS Independent
Classifier: Programming Language :: Python
